{
  "data": {
    "article": {},
    "attachments": {},
    "author_id": "2061323838349340672",
    "conversation_id": "2075486700906889471",
    "created_at": "2026-07-10T08:50:02.000Z",
    "edit_controls": {
      "editable_until": "2026-07-10T09:50:02.000Z",
      "edits_remaining": 5,
      "is_edit_eligible": false
    },
    "edit_history_tweet_ids": [
      "2075502796594692125"
    ],
    "entities": {
      "mentions": [
        {
          "end": 16,
          "id": "1868205822511288320",
          "start": 0,
          "username": "vicoOci_Olvidar"
        }
      ]
    },
    "geo": {},
    "id": "2075502796594692125",
    "in_reply_to_user_id": "1868205822511288320",
    "lang": "ja",
    "note_tweet": {
      "entities": {}
    },
    "possibly_sensitive": false,
    "public_metrics": {
      "bookmark_count": 0,
      "impression_count": 0,
      "like_count": 0,
      "quote_count": 0,
      "reply_count": 0,
      "retweet_count": 0
    },
    "referenced_tweets": [
      {
        "id": "2075486700906889471",
        "type": "replied_to"
      }
    ],
    "reply_settings": "everyone",
    "text": "@vicoOci_Olvidar 我也可以"
  },
  "includes": {
    "media": [
      {
        "height": 2048,
        "media_key": "3_2075486692258316291",
        "public_metrics": {},
        "type": "photo",
        "url": "https://pbs.twimg.com/media/HM2cJnQbgAM4NNn.jpg",
        "width": 1536
      },
      {
        "height": 1536,
        "media_key": "3_2075486692686106625",
        "public_metrics": {},
        "type": "photo",
        "url": "https://pbs.twimg.com/media/HM2cJo2bEAEseNz.jpg",
        "width": 2048
      }
    ],
    "tweets": [
      {
        "article": {},
        "attachments": {},
        "author_id": "2061323838349340672",
        "conversation_id": "2075486700906889471",
        "created_at": "2026-07-10T08:50:02.000Z",
        "edit_controls": {
          "editable_until": "2026-07-10T09:50:02.000Z",
          "edits_remaining": 5,
          "is_edit_eligible": false
        },
        "edit_history_tweet_ids": [
          "2075502796594692125"
        ],
        "entities": {
          "mentions": [
            {
              "end": 16,
              "id": "1868205822511288320",
              "start": 0,
              "username": "vicoOci_Olvidar"
            }
          ]
        },
        "geo": {},
        "id": "2075502796594692125",
        "in_reply_to_user_id": "1868205822511288320",
        "lang": "ja",
        "note_tweet": {
          "entities": {}
        },
        "possibly_sensitive": false,
        "public_metrics": {
          "bookmark_count": 0,
          "impression_count": 0,
          "like_count": 0,
          "quote_count": 0,
          "reply_count": 0,
          "retweet_count": 0
        },
        "referenced_tweets": [
          {
            "id": "2075486700906889471",
            "type": "replied_to"
          }
        ],
        "reply_settings": "everyone",
        "text": "@vicoOci_Olvidar 我也可以"
      },
      {
        "article": {},
        "attachments": {
          "media_keys": [
            "3_2075486692258316291",
            "3_2075486692686106625"
          ]
        },
        "author_id": "1868205822511288320",
        "conversation_id": "2075486700906889471",
        "created_at": "2026-07-10T07:46:04.000Z",
        "edit_controls": {
          "editable_until": "2026-07-10T08:46:04.000Z",
          "edits_remaining": 5,
          "is_edit_eligible": true
        },
        "edit_history_tweet_ids": [
          "2075486700906889471"
        ],
        "entities": {
          "urls": [
            {
              "display_url": "pic.x.com/DqpG5RMrQA",
              "end": 37,
              "expanded_url": "https://x.com/vicoOci_Olvidar/status/2075486700906889471/photo/1",
              "media_key": "3_2075486692258316291",
              "start": 14,
              "url": "https://t.co/DqpG5RMrQA"
            },
            {
              "display_url": "pic.x.com/DqpG5RMrQA",
              "end": 37,
              "expanded_url": "https://x.com/vicoOci_Olvidar/status/2075486700906889471/photo/1",
              "media_key": "3_2075486692686106625",
              "start": 14,
              "url": "https://t.co/DqpG5RMrQA"
            }
          ]
        },
        "geo": {},
        "id": "2075486700906889471",
        "lang": "zh",
        "note_tweet": {
          "entities": {}
        },
        "possibly_sensitive": false,
        "public_metrics": {
          "bookmark_count": 0,
          "impression_count": 100,
          "like_count": 14,
          "quote_count": 0,
          "reply_count": 3,
          "retweet_count": 0
        },
        "reply_settings": "everyone",
        "text": "你怎么对我的袜子做那种事😡 https://t.co/DqpG5RMrQA"
      }
    ],
    "users": [
      {
        "created_at": "2026-06-01T06:00:50.000Z",
        "description": "这里是三崎同时也是南枳，是我和我的爱人共同的帐号，58/138🚪，欢迎精神病死毒虫地雷女来找我玩，卖各种药的小女孩",
        "id": "2061323838349340672",
        "name": "三崎南枝",
        "profile_image_url": "https://pbs.twimg.com/profile_images/2061329806676131840/dbADJoMO_normal.jpg",
        "protected": false,
        "public_metrics": {
          "followers_count": 293,
          "following_count": 276,
          "like_count": 2473,
          "listed_count": 0,
          "media_count": 26,
          "tweet_count": 455
        },
        "url": "",
        "username": "misakinae8964",
        "verified": false
      },
      {
        "created_at": "2024-12-15T08:06:14.000Z",
        "description": "我愛的人幸福就好呀｜養我的主人 @D_D_ovO_｜😺 @ashasw114514 @misakinae8964 @rinko_zero8964｜歡迎視奸｜asd/gad｜我想成為你的翅膀",
        "entities": {
          "description": {
            "mentions": [
              {
                "end": 25,
                "start": 16,
                "username": "D_D_ovO_"
              },
              {
                "end": 41,
                "start": 28,
                "username": "ashasw114514"
              },
              {
                "end": 56,
                "start": 42,
                "username": "misakinae8964"
              },
              {
                "end": 72,
                "start": 57,
                "username": "rinko_zero8964"
              }
            ]
          }
        },
        "id": "1868205822511288320",
        "location": "床",
        "name": "💿胃名立希◉‿◉",
        "pinned_tweet_id": "2072999358048637429",
        "profile_image_url": "https://pbs.twimg.com/profile_images/2067946652430934016/wQEKA11j_normal.jpg",
        "protected": false,
        "public_metrics": {
          "followers_count": 4672,
          "following_count": 418,
          "like_count": 25301,
          "listed_count": 18,
          "media_count": 1508,
          "tweet_count": 18740
        },
        "url": "",
        "username": "vicoOci_Olvidar",
        "verified": false
      }
    ]
  }
}