{
  "data": {
    "article": {},
    "attachments": {},
    "author_id": "2061323838349340672",
    "conversation_id": "2062404786872594865",
    "created_at": "2026-06-04T12:15:14.000Z",
    "edit_controls": {
      "editable_until": "2026-06-04T13:15:14.000Z",
      "edits_remaining": 5,
      "is_edit_eligible": false
    },
    "edit_history_tweet_ids": [
      "2062508475595538600"
    ],
    "entities": {
      "mentions": [
        {
          "end": 7,
          "id": "1732356232290222080",
          "start": 0,
          "username": "8964_Y"
        }
      ]
    },
    "geo": {},
    "id": "2062508475595538600",
    "in_reply_to_user_id": "1732356232290222080",
    "lang": "ja",
    "note_tweet": {
      "entities": {}
    },
    "possibly_sensitive": false,
    "public_metrics": {
      "bookmark_count": 0,
      "impression_count": 0,
      "like_count": 0,
      "quote_count": 0,
      "reply_count": 0,
      "retweet_count": 0
    },
    "referenced_tweets": [
      {
        "id": "2062404786872594865",
        "type": "replied_to"
      }
    ],
    "reply_settings": "everyone",
    "text": "@8964_Y 好看！"
  },
  "includes": {
    "media": [
      {
        "height": 800,
        "media_key": "3_2062404781315174400",
        "public_metrics": {},
        "type": "photo",
        "url": "https://pbs.twimg.com/media/HJ8iOLVbsAAW_Gu.jpg",
        "width": 800
      }
    ],
    "tweets": [
      {
        "article": {},
        "attachments": {},
        "author_id": "2061323838349340672",
        "conversation_id": "2062404786872594865",
        "created_at": "2026-06-04T12:15:14.000Z",
        "edit_controls": {
          "editable_until": "2026-06-04T13:15:14.000Z",
          "edits_remaining": 5,
          "is_edit_eligible": false
        },
        "edit_history_tweet_ids": [
          "2062508475595538600"
        ],
        "entities": {
          "mentions": [
            {
              "end": 7,
              "id": "1732356232290222080",
              "start": 0,
              "username": "8964_Y"
            }
          ]
        },
        "geo": {},
        "id": "2062508475595538600",
        "in_reply_to_user_id": "1732356232290222080",
        "lang": "ja",
        "note_tweet": {
          "entities": {}
        },
        "possibly_sensitive": false,
        "public_metrics": {
          "bookmark_count": 0,
          "impression_count": 0,
          "like_count": 0,
          "quote_count": 0,
          "reply_count": 0,
          "retweet_count": 0
        },
        "referenced_tweets": [
          {
            "id": "2062404786872594865",
            "type": "replied_to"
          }
        ],
        "reply_settings": "everyone",
        "text": "@8964_Y 好看！"
      },
      {
        "article": {},
        "attachments": {
          "media_keys": [
            "3_2062404781315174400"
          ]
        },
        "author_id": "1732356232290222080",
        "conversation_id": "2062404786872594865",
        "created_at": "2026-06-04T05:23:13.000Z",
        "edit_controls": {
          "editable_until": "2026-06-04T06:23:13.000Z",
          "edits_remaining": 5,
          "is_edit_eligible": true
        },
        "edit_history_tweet_ids": [
          "2062404786872594865"
        ],
        "entities": {
          "urls": [
            {
              "display_url": "pic.x.com/J7c0hUUgsK",
              "end": 23,
              "expanded_url": "https://x.com/8964_Y/status/2062404786872594865/photo/1",
              "media_key": "3_2062404781315174400",
              "start": 0,
              "url": "https://t.co/J7c0hUUgsK"
            }
          ]
        },
        "geo": {},
        "id": "2062404786872594865",
        "lang": "zxx",
        "note_tweet": {
          "entities": {}
        },
        "possibly_sensitive": false,
        "public_metrics": {
          "bookmark_count": 0,
          "impression_count": 208,
          "like_count": 26,
          "quote_count": 0,
          "reply_count": 1,
          "retweet_count": 0
        },
        "reply_settings": "everyone",
        "text": "https://t.co/J7c0hUUgsK"
      }
    ],
    "users": [
      {
        "created_at": "2026-06-01T06:00:50.000Z",
        "description": "这里是三崎同时也是南枳，是我和我的爱人共同的帐号，58/138🚪，欢迎精神病死毒虫地雷女来找我玩，私信我解锁化学物质",
        "id": "2061323838349340672",
        "name": "三崎南枝",
        "profile_image_url": "https://pbs.twimg.com/profile_images/2061329806676131840/dbADJoMO_normal.jpg",
        "protected": false,
        "public_metrics": {
          "followers_count": 19,
          "following_count": 64,
          "like_count": 152,
          "listed_count": 0,
          "media_count": 5,
          "tweet_count": 24
        },
        "username": "misakinae8964",
        "verified": false
      },
      {
        "created_at": "2023-12-06T11:08:15.000Z",
        "description": "希望您能多了解我一点｜专门发画的：@QY_art7 只会过信任的人的账号@whxsa11 ｜多靠近我一些吧｜🚪300/520无区别纯绿",
        "entities": {
          "description": {
            "mentions": [
              {
                "end": 25,
                "start": 17,
                "username": "QY_art7"
              },
              {
                "end": 44,
                "start": 36,
                "username": "whxsa11"
              }
            ]
          }
        },
        "id": "1732356232290222080",
        "location": "神域市",
        "name": "洇魔女だ",
        "pinned_tweet_id": "2060367314638581995",
        "profile_image_url": "https://pbs.twimg.com/profile_images/2038658610172157953/Vgc3WGox_normal.jpg",
        "protected": false,
        "public_metrics": {
          "followers_count": 6229,
          "following_count": 738,
          "like_count": 23799,
          "listed_count": 19,
          "media_count": 1120,
          "tweet_count": 16436
        },
        "username": "8964_Y",
        "verified": false
      }
    ]
  }
}